sshUploadandDownloadFileFolder.py
sshUploadandDownloadFileFolder-2.0.dist-info/METADATA
sshUploadandDownloadFileFolder-2.0.dist-info/WHEEL
sshUploadandDownloadFileFolder-2.0.dist-info/top_level.txt
sshUploadandDownloadFileFolder-2.0.dist-info/RECORD
