Metadata-Version: 2.1
Name: sshUploadandDownloadFileFolder
Version: 2.0
Summary: MZCL
Home-page: https://github.com/yourusername/yourmodule
Author: pythonking
Author-email: woshilaijiajunya@126.com
